[
	{
		"mm_ind_sys_id" : 748868,
		"bnk_code" : "40",
		"branchcode" : "123",
		"customerid" : "6071016569",
		"ind_birth_date" : "1982-07-24",
		"ind_name" : "Sengaloun",
		"ind_second_name" : "",
		"ind_surname" : "Boutnouanchaleun",
		"ind_lao_name" : "ແສງອາລຸນ",
		"ind_lao_surname" : "ບຸດນວນຈະເລີນ",
		"ind_old_surname" : "",
		"ind_lao_old_surname" : "",
		"ind_nationality" : "LA",
		"ind_gender" : "F",
		"ind_civil_status" : "S",
		"ind_insert_date" : "2020-06-09 15:28:18",
		"ind_update_date" : "2020-04-29 14:14:25",
		"mm_action_date" : null,
		"blk_sys_id" : 35977,
		"mm_status" : "U"
	},
	{
		"mm_ind_sys_id" : 1218613,
		"bnk_code" : "40",
		"branchcode" : "123",
		"customerid" : "6071004921",
		"ind_birth_date" : "1981-05-21",
		"ind_name" : "Phouangpheth",
		"ind_second_name" : "",
		"ind_surname" : "Siviengphanom",
		"ind_lao_name" : "ພວງເພັດ",
		"ind_lao_surname" : "ສີວຽງພະນົມ",
		"ind_old_surname" : "",
		"ind_lao_old_surname" : "",
		"ind_nationality" : "LA",
		"ind_gender" : "F",
		"ind_civil_status" : "S",
		"ind_insert_date" : "2020-06-09 15:28:17",
		"ind_update_date" : "2020-04-29 14:14:25",
		"mm_action_date" : "2023-01-25 13:57:26",
		"blk_sys_id" : 35977,
		"mm_status" : "M"
	},
	{
		"mm_ind_sys_id" : 1244065,
		"bnk_code" : "40",
		"branchcode" : "123",
		"customerid" : "6071017339",
		"ind_birth_date" : "1976-02-06",
		"ind_name" : "Kongkeo",
		"ind_second_name" : "",
		"ind_surname" : "Vilaysack",
		"ind_lao_name" : "ກອງແກ້ວ",
		"ind_lao_surname" : "ວິໄລສັກ",
		"ind_old_surname" : "",
		"ind_lao_old_surname" : "",
		"ind_nationality" : "LA",
		"ind_gender" : "F",
		"ind_civil_status" : "M",
		"ind_insert_date" : "2020-06-09 15:28:17",
		"ind_update_date" : "2020-04-29 14:14:25",
		"mm_action_date" : null,
		"blk_sys_id" : 35977,
		"mm_status" : "U"
	},
	{
		"mm_ind_sys_id" : 1253052,
		"bnk_code" : "40",
		"branchcode" : "123",
		"customerid" : "6071016506",
		"ind_birth_date" : "1964-12-22",
		"ind_name" : "Guangping",
		"ind_second_name" : "",
		"ind_surname" : "Qin",
		"ind_lao_name" : "",
		"ind_lao_surname" : "",
		"ind_old_surname" : "",
		"ind_lao_old_surname" : "",
		"ind_nationality" : "CN",
		"ind_gender" : "M",
		"ind_civil_status" : "M",
		"ind_insert_date" : "2020-06-09 15:28:17",
		"ind_update_date" : "2020-04-29 14:14:25",
		"mm_action_date" : null,
		"blk_sys_id" : 35977,
		"mm_status" : "A"
	},
	{
		"mm_ind_sys_id" : 1253053,
		"bnk_code" : "40",
		"branchcode" : "123",
		"customerid" : "6071002392",
		"ind_birth_date" : "1978-06-05",
		"ind_name" : "Kongtavanh",
		"ind_second_name" : "",
		"ind_surname" : "Keodouangsinh",
		"ind_lao_name" : "ກົງຕາວັນ",
		"ind_lao_surname" : "ແກ້ວດວງສິນ",
		"ind_old_surname" : "",
		"ind_lao_old_surname" : "",
		"ind_nationality" : "LA",
		"ind_gender" : "F",
		"ind_civil_status" : "S",
		"ind_insert_date" : "2020-06-09 15:28:17",
		"ind_update_date" : "2020-04-29 14:14:25",
		"mm_action_date" : null,
		"blk_sys_id" : 35977,
		"mm_status" : "A"
	},
	{
		"mm_ind_sys_id" : 1253054,
		"bnk_code" : "40",
		"branchcode" : "123",
		"customerid" : "6071015598",
		"ind_birth_date" : "1979-10-18",
		"ind_name" : "Kai",
		"ind_second_name" : "",
		"ind_surname" : "Li",
		"ind_lao_name" : "",
		"ind_lao_surname" : "",
		"ind_old_surname" : "",
		"ind_lao_old_surname" : "",
		"ind_nationality" : "CN",
		"ind_gender" : "M",
		"ind_civil_status" : "M",
		"ind_insert_date" : "2020-06-09 15:28:17",
		"ind_update_date" : "2020-04-29 14:14:25",
		"mm_action_date" : null,
		"blk_sys_id" : 35977,
		"mm_status" : "A"
	},
	{
		"mm_ind_sys_id" : 1253055,
		"bnk_code" : "40",
		"branchcode" : "123",
		"customerid" : "6071007096",
		"ind_birth_date" : "1984-03-27",
		"ind_name" : "Shuang",
		"ind_second_name" : "",
		"ind_surname" : "Li",
		"ind_lao_name" : "",
		"ind_lao_surname" : "",
		"ind_old_surname" : "",
		"ind_lao_old_surname" : "",
		"ind_nationality" : "CN",
		"ind_gender" : "M",
		"ind_civil_status" : "M",
		"ind_insert_date" : "2020-06-09 15:28:17",
		"ind_update_date" : "2020-04-29 14:14:25",
		"mm_action_date" : null,
		"blk_sys_id" : 35977,
		"mm_status" : "A"
	},
	{
		"mm_ind_sys_id" : 1253056,
		"bnk_code" : "40",
		"branchcode" : "123",
		"customerid" : "6071016504",
		"ind_birth_date" : "1967-11-06",
		"ind_name" : "Wei",
		"ind_second_name" : "",
		"ind_surname" : "Ye",
		"ind_lao_name" : "",
		"ind_lao_surname" : "",
		"ind_old_surname" : "",
		"ind_lao_old_surname" : "",
		"ind_nationality" : "CN",
		"ind_gender" : "M",
		"ind_civil_status" : "M",
		"ind_insert_date" : "2020-06-09 15:28:17",
		"ind_update_date" : "2020-04-29 14:14:25",
		"mm_action_date" : null,
		"blk_sys_id" : 35977,
		"mm_status" : "A"
	},
	{
		"mm_ind_sys_id" : 1253057,
		"bnk_code" : "40",
		"branchcode" : "123",
		"customerid" : "6071016521",
		"ind_birth_date" : "1979-02-02",
		"ind_name" : "Lin",
		"ind_second_name" : "",
		"ind_surname" : "Sun",
		"ind_lao_name" : "",
		"ind_lao_surname" : "",
		"ind_old_surname" : "",
		"ind_lao_old_surname" : "",
		"ind_nationality" : "CN",
		"ind_gender" : "F",
		"ind_civil_status" : "M",
		"ind_insert_date" : "2020-06-09 15:28:17",
		"ind_update_date" : "2020-04-29 14:14:25",
		"mm_action_date" : null,
		"blk_sys_id" : 35977,
		"mm_status" : "A"
	},
	{
		"mm_ind_sys_id" : 1253058,
		"bnk_code" : "40",
		"branchcode" : "123",
		"customerid" : "6071003361",
		"ind_birth_date" : "1977-06-16",
		"ind_name" : "Hui",
		"ind_second_name" : "",
		"ind_surname" : "Wang",
		"ind_lao_name" : "",
		"ind_lao_surname" : "",
		"ind_old_surname" : "",
		"ind_lao_old_surname" : "",
		"ind_nationality" : "CN",
		"ind_gender" : "M",
		"ind_civil_status" : "M",
		"ind_insert_date" : "2020-06-09 15:28:17",
		"ind_update_date" : "2020-04-29 14:14:25",
		"mm_action_date" : null,
		"blk_sys_id" : 35977,
		"mm_status" : "A"
	},
	{
		"mm_ind_sys_id" : 1253059,
		"bnk_code" : "40",
		"branchcode" : "123",
		"customerid" : "6071016660",
		"ind_birth_date" : "1976-02-01",
		"ind_name" : "Zhaolong",
		"ind_second_name" : "",
		"ind_surname" : "Ge",
		"ind_lao_name" : "",
		"ind_lao_surname" : "",
		"ind_old_surname" : "",
		"ind_lao_old_surname" : "",
		"ind_nationality" : "CN",
		"ind_gender" : "M",
		"ind_civil_status" : "S",
		"ind_insert_date" : "2020-06-09 15:28:17",
		"ind_update_date" : "2020-04-29 14:14:25",
		"mm_action_date" : null,
		"blk_sys_id" : 35977,
		"mm_status" : "A"
	},
	{
		"mm_ind_sys_id" : 1253060,
		"bnk_code" : "40",
		"branchcode" : "123",
		"customerid" : "6071001362",
		"ind_birth_date" : "1976-10-25",
		"ind_name" : "Tianyi",
		"ind_second_name" : "",
		"ind_surname" : "Zhang",
		"ind_lao_name" : "",
		"ind_lao_surname" : "",
		"ind_old_surname" : "",
		"ind_lao_old_surname" : "",
		"ind_nationality" : "CN",
		"ind_gender" : "M",
		"ind_civil_status" : "S",
		"ind_insert_date" : "2020-06-09 15:28:17",
		"ind_update_date" : "2020-04-29 14:14:25",
		"mm_action_date" : null,
		"blk_sys_id" : 35977,
		"mm_status" : "A"
	},
	{
		"mm_ind_sys_id" : 1253061,
		"bnk_code" : "40",
		"branchcode" : "123",
		"customerid" : "6071016249",
		"ind_birth_date" : "1982-04-23",
		"ind_name" : "Gang",
		"ind_second_name" : "",
		"ind_surname" : "Song",
		"ind_lao_name" : "",
		"ind_lao_surname" : "",
		"ind_old_surname" : "",
		"ind_lao_old_surname" : "",
		"ind_nationality" : "CN",
		"ind_gender" : "M",
		"ind_civil_status" : "S",
		"ind_insert_date" : "2020-06-09 15:28:18",
		"ind_update_date" : "2020-04-29 14:14:25",
		"mm_action_date" : null,
		"blk_sys_id" : 35977,
		"mm_status" : "A"
	},
	{
		"mm_ind_sys_id" : 1253062,
		"bnk_code" : "40",
		"branchcode" : "123",
		"customerid" : "6071017343",
		"ind_birth_date" : "1980-09-03",
		"ind_name" : "Laifai",
		"ind_second_name" : "",
		"ind_surname" : "Hong",
		"ind_lao_name" : "",
		"ind_lao_surname" : "",
		"ind_old_surname" : "",
		"ind_lao_old_surname" : "",
		"ind_nationality" : "CN",
		"ind_gender" : "M",
		"ind_civil_status" : "M",
		"ind_insert_date" : "2020-06-09 15:28:18",
		"ind_update_date" : "2020-04-29 14:14:25",
		"mm_action_date" : null,
		"blk_sys_id" : 35977,
		"mm_status" : "A"
	},
	{
		"mm_ind_sys_id" : 1253063,
		"bnk_code" : "40",
		"branchcode" : "123",
		"customerid" : "6071019525",
		"ind_birth_date" : "1975-10-15",
		"ind_name" : "Songzhi",
		"ind_second_name" : "",
		"ind_surname" : "Li",
		"ind_lao_name" : "",
		"ind_lao_surname" : "",
		"ind_old_surname" : "",
		"ind_lao_old_surname" : "",
		"ind_nationality" : "CN",
		"ind_gender" : "M",
		"ind_civil_status" : "O",
		"ind_insert_date" : "2020-06-09 15:28:18",
		"ind_update_date" : "2020-04-29 14:14:25",
		"mm_action_date" : null,
		"blk_sys_id" : 35977,
		"mm_status" : "A"
	},
	{
		"mm_ind_sys_id" : 1307384,
		"bnk_code" : "40",
		"branchcode" : "123",
		"customerid" : "6071014542",
		"ind_birth_date" : "1968-03-25",
		"ind_name" : "Bin",
		"ind_second_name" : "",
		"ind_surname" : "Zhang",
		"ind_lao_name" : "",
		"ind_lao_surname" : "",
		"ind_old_surname" : "",
		"ind_lao_old_surname" : "",
		"ind_nationality" : "CN",
		"ind_gender" : "M",
		"ind_civil_status" : "S",
		"ind_insert_date" : "2020-11-19 15:53:56",
		"ind_update_date" : "2020-11-02 14:14:25",
		"mm_action_date" : null,
		"blk_sys_id" : 35977,
		"mm_status" : "A"
	},
	{
		"mm_ind_sys_id" : 1355588,
		"bnk_code" : "40",
		"branchcode" : "123",
		"customerid" : "6071015989",
		"ind_birth_date" : "1973-05-20",
		"ind_name" : "Rong",
		"ind_second_name" : "",
		"ind_surname" : "Li",
		"ind_lao_name" : "ລີຢົງ",
		"ind_lao_surname" : "",
		"ind_old_surname" : "",
		"ind_lao_old_surname" : "",
		"ind_nationality" : "CN",
		"ind_gender" : "F",
		"ind_civil_status" : "M",
		"ind_insert_date" : "2021-04-06 11:03:16",
		"ind_update_date" : "2021-04-02 11:17:30",
		"mm_action_date" : null,
		"blk_sys_id" : 35977,
		"mm_status" : "A"
	},
	{
		"mm_ind_sys_id" : 1437875,
		"bnk_code" : "40",
		"branchcode" : "123",
		"customerid" : "6071022734",
		"ind_birth_date" : "1989-06-07",
		"ind_name" : "Jin",
		"ind_second_name" : "",
		"ind_surname" : "Liu",
		"ind_lao_name" : "ຈີນລີວ",
		"ind_lao_surname" : "",
		"ind_old_surname" : "",
		"ind_lao_old_surname" : "",
		"ind_nationality" : "CN",
		"ind_gender" : "M",
		"ind_civil_status" : "S",
		"ind_insert_date" : "2021-06-29 08:57:45",
		"ind_update_date" : "2021-06-04 15:17:30",
		"mm_action_date" : null,
		"blk_sys_id" : 35977,
		"mm_status" : "A"
	}
]
